<?xml version="1.0" encoding="utf-8"?>
<LanguageData>
  <!--The following translations were generated by https://www.deepl.com/-->
  <MsgTouchAnimalJoin>Die sanfte Berührung von {0} veranlasst {1} geschickt, sich {2} anzuschließen.</MsgTouchAnimalJoin>
  <MsgAddictionTouchAnimal>{0} ist süchtig danach, die {1} zu berühren. Wenn {0} die {1} nicht regelmäßig berührt, beginnt die Entzugsreaktion.</MsgAddictionTouchAnimal>
  <TitleAnimalsWantToTouch>Tiere wollen berühren</TitleAnimalsWantToTouch>
  <TitleAssumedSkillLevel>Angenommenes Qualifikationsniveau</TitleAssumedSkillLevel>
  <TitleTouchBehaviorInformation>Info zum Anfassen von Tieren</TitleTouchBehaviorInformation>
  <LabelAnimalKind>Tierart</LabelAnimalKind>
  <LabelAnimalSkillRequire>Tierische Fähigkeiten erfordern</LabelAnimalSkillRequire>
  <LabelChanceToJoin>Chance zum Beitritt</LabelChanceToJoin>
  <LabelWillTouch>Wird berühren</LabelWillTouch>
  <LabelWontTouch>Wird nicht berührt</LabelWontTouch>
</LanguageData>
